stability_ai_api/__init__.py
stability_ai_api/basic_types.py
stability_ai_api/constants.py
stability_ai_api/query_config.py
stability_ai_api/stability_ai_api.py
stability_ai_api-0.0.1.dist-info/LICENSE
stability_ai_api-0.0.1.dist-info/METADATA
stability_ai_api-0.0.1.dist-info/WHEEL
stability_ai_api-0.0.1.dist-info/top_level.txt
stability_ai_api-0.0.1.dist-info/RECORD
