Metadata-Version: 2.1
Name: stability-ai-api
Version: 0.0.1
Summary: A small API wrapper to interact with the Stability AI API.
Author-email: Flávio De Melo <flavio.eler@gmail.com>
Maintainer-email: Flávio De Melo <flavio.eler@gmail.com>
License: Apache Software License 2.0
Project-URL: bugs, https://github.com/femelo/stability-ai-api/issues
Project-URL: changelog, https://github.com/femelo/stability-ai-api/blob/main/changelog.md
Project-URL: homepage, https://github.com/femelo/stability-ai-api
License-File: LICENSE
Requires-Dist: pydantic ~=2.7.1
Requires-Dist: requests
Provides-Extra: dev
Requires-Dist: coverage ; extra == 'dev'
Requires-Dist: mypy ; extra == 'dev'
Requires-Dist: pytest ; extra == 'dev'
Requires-Dist: ruff ; extra == 'dev'
